{
    "speakers": {
        "npc": {
            "name": "     ",
            "face": {
                "type": "artificial",
                "modelType": "npc",
                "identifier": "cobblemon:monsieur",
                "isLeftSide": true
            }
        }
    },
    "pages": [
        {
            "id": "page1",
            "speaker": "npc",
            "lines": [
                "What\u2019s the hustle, little Crustle? Welcome to Santalune City Gym!"
            ],
            "input": {
                "type": "option",
                "vertical": false,
                "options": [
                    {
                        "text": "Next",
                        "value": "next",
                        "action": "q.dialogue.set_page('page2');"
                    }
                ]
            }
        },
        {
            "id": "page2",
            "speaker": "npc",
            "lines": [
                "So, future Champ, this\u2019ll be your first time challenging a Gym, huh? Are you thrilled? Are you pumped?"
            ],
            "input": {
                "type": "option",
                "vertical": false,
                "options": [
                    {
                        "text": "Next",
                        "value": "next",
                        "action": "q.dialogue.set_page('page3');"
                    }
                ]
            }
        },
        {
            "id": "page3",
            "speaker": "npc",
            "lines": [
                "You should be! No worries here! You\u2019ve got Pok\u00e9mon on your side!"
            ],
            "input": {
                "type": "option",
                "vertical": false,
                "options": [
                    {
                        "text": "Next",
                        "value": "next",
                        "action": "q.dialogue.set_page('page4');"
                    }
                ]
            }
        },
        {
            "id": "page4",
            "speaker": "npc",
            "lines": [
                "And really, they\u2019re the ones who are gonna be doing all the battling. Am I right or am I right? Right?"
            ],
            "input": {
                "type": "option",
                "vertical": false,
                "options": [
                    {
                        "text": "Close",
                        "value": "close",
                        "action": [
                            "q.dialogue.close();"
                        ]
                    }
                ]
            }
        }
    ]
}