{
  "abomasnow": {"sounds": ["abomasnow"]},
  "articuno": {"sounds": ["articuno"]},
  "berryget": {"sounds": ["berryget"]},
  "caves": {"sounds": ["caves"]},
  "espurr": {"sounds": ["espurr"]},
  "fletchling": {"sounds": ["fletchling"]},
  "gymbadgeget": {"sounds": ["gymbadgeget"]},
  "gymlumiosequiz": {"sounds": ["gymlumiosequiz"]},
  "lookerchapter": {"sounds": ["lookerchapter"]},
  "lucario": {"sounds": ["lucario"]},
  "mamoswine": {"sounds": ["mamoswine"]},
  "megastoneget": {"sounds": ["megastoneget"]},
  "mewtwo": {"sounds": ["mewtwo"]},
  "moltres": {"sounds": ["moltres"]},
  "output.txt": {"sounds": ["output.txt"]},
  "pokeflute": {"sounds": ["pokeflute"]},
  "skiddo": {"sounds": ["skiddo"]},
  "snorlax": {"sounds": ["snorlax"]},
  "tmv": {"sounds": ["tmv"]},
  "waterdrops": {"sounds": ["waterdrops"]},
  "xerneas": {"sounds": ["xerneas"]},
  "yveltal": {"sounds": ["yveltal"]},
  "zapdos": {"sounds": ["zapdos"]},
  "zygarde": {"sounds": ["zygarde"]},

  "heal": {"sounds": ["heal"]},
  "itemget": {"sounds": ["itemget"]}
}
